vspace/__init__.py
vspace/hyak.py
vspace/vspace.py
vspace/vspace_hyak.py
vspace/vspace_version.py
vspace-2.3.2.dist-info/LICENSE
vspace-2.3.2.dist-info/METADATA
vspace-2.3.2.dist-info/WHEEL
vspace-2.3.2.dist-info/entry_points.txt
vspace-2.3.2.dist-info/top_level.txt
vspace-2.3.2.dist-info/RECORD
