Metadata-Version: 2.1
Name: vspace
Version: 2.3.2
Summary: VPLANET parameter sweep helper
Home-page: https://github.com/VirtualPlanetaryLaboratory/vspace
Author: Russell Deitrick
Author-email: rdeitrick@uvic.ca
License: MIT
License-File: LICENSE
Requires-Dist: numpy
Requires-Dist: matplotlib
Requires-Dist: argparse
Requires-Dist: astropy
